RnDPackage/Datasets.py
RnDPackage/__init__.py
RnDPackage/data/WPP2019_TotalPopulationBySex.csv
RnDPackage/data/covid_19_clean_complete.csv
RnDPackage-0.20.dist-info/METADATA
RnDPackage-0.20.dist-info/WHEEL
RnDPackage-0.20.dist-info/top_level.txt
RnDPackage-0.20.dist-info/RECORD
