Metadata-Version: 2.1
Name: RnDPackage
Version: 0.20
Summary: Shared packages for R&D projects
Home-page: https://github.com/mehtarjt/python
Author: RnD
Author-email: mehtarjt@gmail.com
License: MIT
Platform: UNKNOWN
